nanoreactor_processing/__init__.py
nanoreactor_processing/nanoreactor_network.py
nanoreactor_processing/nanosim_class.py
nanoreactor_processing/plot_tools.py
nanoreactor_processing/read_write_utils.py
nanoreactor_processing/utils.py
nanoreactor_processing-1.1.1.dist-info/LICENSE.md
nanoreactor_processing-1.1.1.dist-info/METADATA
nanoreactor_processing-1.1.1.dist-info/WHEEL
nanoreactor_processing-1.1.1.dist-info/top_level.txt
nanoreactor_processing-1.1.1.dist-info/RECORD
