Metadata-Version: 2.1
Name: nanoreactor-processing
Version: 1.1.1
Summary: Automated evaluation of computational nanoreactor simulations
Home-page: https://github.com/ochsenfeld-lab/nanoreactor_processing
Download-URL: https://github.com/ochsenfeld-lab/nanoreactor_processing/archive/refs/heads/main.zip
Author: Alexandra Stan
Author-email: alexandra.stan@cup.uni-muenchen.de
License: MIT
Keywords: computational chemistry,automated,molecular dynamics,chemical reactions,ab initio nanoreactor,rdkit
Classifier: Development Status :: 5 - Production/Stable
Classifier: Environment :: Console
Classifier: License :: OSI Approved :: MIT License
Classifier: Programming Language :: Python :: 3.8
License-File: LICENSE.md
Requires-Dist: numpy (>=1.23.1)
Requires-Dist: scipy (>=1.8.1)
Requires-Dist: pandas (>=1.4.3)
Requires-Dist: networkx (>=2.8.4)
Requires-Dist: matplotlib (>=3.5.2)
Requires-Dist: seaborn (>=0.11.2)
Requires-Dist: pyvis (>=0.2.1)
Requires-Dist: rdkit-pypi (==2021.3.4)
